LICENSE
MANIFEST.in
setup.py
conn_utils.egg-info/PKG-INFO
conn_utils.egg-info/SOURCES.txt
conn_utils.egg-info/dependency_links.txt
conn_utils.egg-info/top_level.txt
conn_utils/package/__init__.py
conn_utils/package/_package.py
conn_utils/package/__pycache__/__init__.cpython-311.pyc
conn_utils/package/__pycache__/_package.cpython-311.pyc
conn_utils/yubitusoft/conn_utils/__init__.py
conn_utils/yubitusoft/conn_utils/util/__init__.py